asdk_plugin_accounting/__init__.py
asdk_plugin_accounting/api_registry.py
asdk_plugin_accounting/domain_apis_list.json
asdk_plugin_accounting/agraph/__init__.py
asdk_plugin_accounting/agraph/accounting/__init__.py
asdk_plugin_accounting/agraph/accounting/configuration/__init__.py
asdk_plugin_accounting/agraph/accounting/configuration/attribute/__init__.py
asdk_plugin_accounting/agraph/accounting/configuration/attribute/portfolio/__init__.py
asdk_plugin_accounting/agraph/accounting/configuration/attribute/portfolio/records/__init__.py
asdk_plugin_accounting/agraph/accounting/configuration/attribute/portfolio/records/v1/__init__.py
asdk_plugin_accounting/agraph/accounting/configuration/attribute/portfolio/records/v1/PortfolioConfigurationAPI/__init__.py
asdk_plugin_accounting/agraph/accounting/configuration/attribute/portfolio/records/v1/PortfolioConfigurationAPI/api_client.py
asdk_plugin_accounting/agraph/accounting/configuration/attribute/portfolio/records/v1/PortfolioConfigurationAPI/api_response.py
asdk_plugin_accounting/agraph/accounting/configuration/attribute/portfolio/records/v1/PortfolioConfigurationAPI/configuration.py
asdk_plugin_accounting/agraph/accounting/configuration/attribute/portfolio/records/v1/PortfolioConfigurationAPI/exceptions.py
asdk_plugin_accounting/agraph/accounting/configuration/attribute/portfolio/records/v1/PortfolioConfigurationAPI/rest.py
asdk_plugin_accounting/agraph/accounting/configuration/attribute/portfolio/records/v1/PortfolioConfigurationAPI/swagger.json
asdk_plugin_accounting/agraph/accounting/configuration/attribute/portfolio/records/v1/PortfolioConfigurationAPI/api/__init__.py
asdk_plugin_accounting/agraph/accounting/configuration/attribute/portfolio/records/v1/PortfolioConfigurationAPI/api/default_portfolio_configuration_api.py
asdk_plugin_accounting/agraph/accounting/configuration/attribute/portfolio/records/v1/PortfolioConfigurationAPI/models/__init__.py
asdk_plugin_accounting-2.0.0b2.dist-info/METADATA
asdk_plugin_accounting-2.0.0b2.dist-info/WHEEL
asdk_plugin_accounting-2.0.0b2.dist-info/top_level.txt
asdk_plugin_accounting-2.0.0b2.dist-info/RECORD
